odoo/addons/uom_extra_data/README.rst
odoo/addons/uom_extra_data/__init__.py
odoo/addons/uom_extra_data/__manifest__.py
odoo/addons/uom_extra_data/data/uom.xml
odoo/addons/uom_extra_data/i18n/uom_extra_data.pot
odoo/addons/uom_extra_data/readme/CONTRIBUTORS.rst
odoo/addons/uom_extra_data/readme/DESCRIPTION.rst
odoo/addons/uom_extra_data/readme/ROADMAP.rst
odoo/addons/uom_extra_data/static/description/icon.png
odoo/addons/uom_extra_data/static/description/index.html
odoo14_addon_uom_extra_data-14.0.1.0.1.dist-info/METADATA
odoo14_addon_uom_extra_data-14.0.1.0.1.dist-info/WHEEL
odoo14_addon_uom_extra_data-14.0.1.0.1.dist-info/top_level.txt
odoo14_addon_uom_extra_data-14.0.1.0.1.dist-info/RECORD
